reader/__init__.py
reader/__main__.py
reader/analysis/__init__.py
reader/analysis/dialogue_detector.py
reader/analysis/gender_detector.py
reader/api.py
reader/batch/__init__.py
reader/batch/batch_processor.py
reader/batch/neural_processor.py
reader/batch/rich_progress.py
reader/batch/timeseries_progress.py
reader/batch/tqdm_progress.py
reader/chapters/__init__.py
reader/chapters/chapter_manager.py
reader/cli.py
reader/config.py
reader/engines/__init__.py
reader/engines/kokoro_engine.py
reader/interfaces/__init__.py
reader/interfaces/audio_processor.py
reader/interfaces/text_parser.py
reader/interfaces/tts_engine.py
reader/parsers/__init__.py
reader/parsers/epub_parser.py
reader/parsers/pdf_parser.py
reader/parsers/text_parser.py
reader/processors/__init__.py
reader/processors/ffmpeg_processor.py
reader/text_processing/__init__.py
reader/text_processing/number_expander.py
reader/utils/__init__.py
reader/utils/model_downloader.py
reader/utils/setup.py
reader/voices/__init__.py
reader/voices/character_mapper.py
reader/voices/voice_previewer.py
audiobook_reader-0.1.8.dist-info/LICENSE
audiobook_reader-0.1.8.dist-info/METADATA
audiobook_reader-0.1.8.dist-info/WHEEL
audiobook_reader-0.1.8.dist-info/entry_points.txt
audiobook_reader-0.1.8.dist-info/RECORD
