Metadata-Version: 2.3
Name: audiobook-reader
Version: 0.1.8
Summary: AI-powered audiobook generator with GPU/NPU acceleration (up to 8x faster than real-time). Built-in Kokoro-82M TTS with character-aware voices and emotion analysis. Supports EPUB, PDF, TXT, MD, RST (use convertext for DOCX/MOBI/HTML).
License: MIT
Keywords: audiobook,text-to-speech,tts,kokoro,neural-engine,apple-silicon,m1,m2,m3,m4,epub,pdf,cli,audio,conversion,character-voices,emotion-analysis
Author: danielcorsano
Author-email: danielcorsano@users.noreply.github.com
Requires-Python: >=3.10,<3.14
Classifier: Development Status :: 4 - Beta
Classifier: Environment :: Console
Classifier: Intended Audience :: End Users/Desktop
Classifier: License :: OSI Approved :: MIT License
Classifier: Operating System :: OS Independent
Classifier: Programming Language :: Python :: 3
Classifier: Programming Language :: Python :: 3.10
Classifier: Programming Language :: Python :: 3.11
Classifier: Programming Language :: Python :: 3.12
Classifier: Programming Language :: Python :: 3.13
Classifier: Topic :: Multimedia :: Sound/Audio :: Conversion
Classifier: Topic :: Multimedia :: Sound/Audio :: Speech
Classifier: Topic :: Text Processing
Provides-Extra: all
Provides-Extra: monitoring
Provides-Extra: progress-full
Provides-Extra: progress-rich
Provides-Extra: progress-timeseries
Provides-Extra: progress-tqdm
Requires-Dist: PyPDF2 (>=3.0.1,<4.0.0)
Requires-Dist: beautifulsoup4 (>=4.12.2,<5.0.0)
Requires-Dist: click (>=8.1.7,<9.0.0)
Requires-Dist: ebooklib (>=0.18,<0.19)
Requires-Dist: ffmpeg-python (>=0.2.0,<0.3.0)
Requires-Dist: kokoro-onnx (>=0.4.9,<0.5.0)
Requires-Dist: mutagen (>=1.47.0,<2.0.0)
Requires-Dist: onnxruntime (>=1.20.0,<2.0.0)
Requires-Dist: plotext (>=5.3.2,<6.0.0) ; extra == "progress-full" or extra == "progress-timeseries" or extra == "all"
Requires-Dist: psutil (>=7.1.0,<8.0.0) ; extra == "monitoring" or extra == "all"
Requires-Dist: pyyaml (>=6.0.1,<7.0.0)
Requires-Dist: regex (>=2023.12.25,<2024.0.0)
Requires-Dist: rich (>=14.0.0,<15.0.0) ; extra == "progress-full" or extra == "progress-rich" or extra == "all"
Requires-Dist: tqdm (>=4.67.0,<5.0.0) ; extra == "progress-full" or extra == "progress-tqdm" or extra == "all"
Requires-Dist: vaderSentiment (>=3.3.2,<4.0.0)
Project-URL: Documentation, https://github.com/danielcorsano/reader/tree/main/docs
Project-URL: Homepage, https://github.com/danielcorsano/reader
Project-URL: Repository, https://github.com/danielcorsano/reader
